[
  {
    "linkedResources": [
      {
        "linkedResourceType": "Metadata",
        "resourceDescription": "Original Metadata Record",
        "resourceURL": "http://oa.dirisa.org/Institutions/coj/coj/metadata/metadata.2017-06-30.7768909787/getOriginalXml"
      }
    ],
    "publisher": "City Of Johannesburg",
    "rightsList": [
      {
        "rights": "",
        "rightsURI": "https://creativecommons.org/licenses/by/4.0/"
      }
    ],
    "publicationYear": "2003",
    "formats": [
      [
        "SDE Feature Class",
        "ArcInfo cov"
      ]
    ],
    "language": "en-US",
    "contributors": [
      {
        "nameIdentifiers": [
          {
            "nameIdentifierScheme": "",
            "schemeURI": "",
            "nameIdentifier": ""
          }
        ],
        "givenName": "",
        "name": "Corporate Geo-Informatics(CGIS)",
        "contributorType": "DataCurator",
        "affiliations": [
          {
            "affiliation": "Position Name: Projects Section; e-Mail Address: cgisprojects@joburg.org.za; City: Johannesburg; Province: Gauteng; Delivery Point: Corporate GIS Metro Centre Braamfontein; Postal Code: 2000"
          }
        ],
        "familyName": ""
      },
      {
        "nameIdentifiers": [
          {
            "nameIdentifierScheme": "",
            "schemeURI": "",
            "nameIdentifier": ""
          }
        ],
        "givenName": "",
        "name": "Projects Manager",
        "contributorType": "ContactPerson",
        "affiliations": [
          {
            "affiliation": "Position Name: Manager; e-Mail Address: cgisprojects@joburg.org.za; City: Johannesburg; Province: Gauteng; Delivery Point: Corporate Geo-Informatics, 8th floor, Metro Center, Braamfontein; Postal Code: 2000"
          }
        ],
        "familyName": ""
      },
      {
        "nameIdentifiers": [
          {
            "nameIdentifierScheme": "",
            "schemeURI": "",
            "nameIdentifier": ""
          }
        ],
        "givenName": "",
        "name": "Project's section",
        "contributorType": "ContactPerson",
        "affiliations": [
          {
            "affiliation": "Position Name: Manager; e-Mail Address: cgisprojects@joburg.org.za; City: Braamfontein; Province: Gauteng; Delivery Point: 158 Civic Boulevard, 8th floor, Metro Centre; Postal Code: 2017"
          }
        ],
        "familyName": ""
      }
    ],
    "geoLocations": [
      {
        "geoLocationBox": "POLYGON ((-26.528445 27.702679, -26.528445 28.215037, -25.900638 28.215037, -25.900638 27.702679, -26.528445 27.702679))"
      }
    ],
    "identifier": {
      "identifier": "7b42777e208b3375f20f320f15e26a60",
      "identifierType": "plone-id"
    },
    "version": "1.2",
    "resourceType": {
      "resourceType": "mapDigital",
      "resourceTypeGeneral": "Dataset"
    },
    "alternateIdentifiers": [
      {
        "alternateIdentifierType": "Plone",
        "alternateIdentifier": "7b42777e208b3375f20f320f15e26a60"
      }
    ],
    "subjects": [
      {
        "subject": "Downloadable Data"
      },
      {
        "subject": "use zones"
      },
      {
        "subject": "zoning"
      },
      {
        "subject": "town planning zones"
      }
    ],
    "subtitle": "",
    "creators": [
      {
        "nameType": "",
        "nameIdentifiers": [
          {
            "nameIdentifierScheme": "",
            "schemeURI": "",
            "nameIdentifier": ""
          }
        ],
        "givenName": "",
        "name": "City of Johannesburg Metropolitan",
        "affiliations": [
          {
            "affiliation": "City of Johannesburg Metropolitan"
          }
        ],
        "familyName": ""
      }
    ],
    "descriptions": [
      {
        "descriptionType": "Abstract",
        "description": "Area indicating a restriction or what use is permitted/imposed on the erection and use of buildings in terms of the use."
      }
    ],
    "titles": [
      {
        "title": "LIS_PROD.LIS.SP_ZONING"
      }
    ],
    "immutableResource": {
      "resourceURL": "download link unavailable"
    }
  },
  {
    "linkedResources": [
      {
        "linkedResourceType": "Metadata",
        "resourceDescription": "Original Metadata Record",
        "resourceURL": "http://oa.dirisa.org/Institutions/coj/coj/metadata/meta152423886183/getOriginalXml"
      }
    ],
    "publisher": "City of Johannesburg",
    "rightsList": [
      {
        "rights": "",
        "rightsURI": "https://creativecommons.org/licenses/by/4.0/"
      }
    ],
    "publicationYear": "2018",
    "formats": [
      [
        "Shapefile",
        "Arcifo"
      ]
    ],
    "language": "en-US",
    "contributors": [
      {
        "nameIdentifiers": [
          {
            "nameIdentifierScheme": "",
            "schemeURI": "",
            "nameIdentifier": ""
          }
        ],
        "givenName": "",
        "name": "GIS Manager",
        "contributorType": "DataCurator",
        "affiliations": [
          {
            "affiliation": "Organisation: City of Johannesburg;  Position Name: Corporate Geo-Informatics (CGIS)"
          }
        ],
        "familyName": ""
      },
      {
        "nameIdentifiers": [
          {
            "nameIdentifierScheme": "",
            "schemeURI": "",
            "nameIdentifier": ""
          }
        ],
        "givenName": "",
        "name": "Corporate Geo-Informatics",
        "contributorType": "DataCurator",
        "affiliations": [
          {
            "affiliation": "Organisation: City of Johannesburg;  Position Name: Manager"
          }
        ],
        "familyName": ""
      }
    ],
    "geoLocations": [
      {
        "geoLocationBox": "POLYGON ((-26.572072 27.738947, -26.572072 28.254735, -25.904089 28.254735, -25.904089 27.738947, -26.572072 27.738947))"
      }
    ],
    "dates": [
      {
        "date": {
          "lte": "2018-04-13",
          "gte": "2018-04-13"
        },
        "dateType": "Created"
      },
      {
        "date": {
          "lte": "2018-04-19",
          "gte": "2018-04-19"
        },
        "dateType": "Issued"
      }
    ],
    "identifier": {
      "identifier": "fc28d52a8231dedbdfda1035440176ce",
      "identifierType": "plone-id"
    },
    "version": "1.2",
    "resourceType": {
      "resourceType": "mapDigital",
      "resourceTypeGeneral": "Dataset"
    },
    "alternateIdentifiers": [
      {
        "alternateIdentifierType": "Plone",
        "alternateIdentifier": "fc28d52a8231dedbdfda1035440176ce"
      }
    ],
    "subjects": [
      {
        "subject": "Downloadable Data"
      }
    ],
    "subtitle": "",
    "creators": [
      {
        "nameType": "",
        "nameIdentifiers": [
          {
            "nameIdentifierScheme": "",
            "schemeURI": "",
            "nameIdentifier": ""
          }
        ],
        "givenName": "",
        "name": "Corporate Geo-Informatics",
        "affiliations": [
          {
            "affiliation": "Organisation: City of Johannesburg;  Position Name: Manager"
          }
        ],
        "familyName": ""
      }
    ],
    "descriptions": [
      {
        "descriptionType": "Abstract",
        "description": "Captured with heights of buildings for specific areas as determined by Development Planning and Facilitation Cbds are Johannesburg, Randburg, Roodepoort, Sandton, Midrand, Baralink and Jabulani Priority 1. CBDs Priority 2. Business, Commercial, Industrial, Special - Zoning Priority 3. 1000 metres of a Railway Station Priority 4. 500 metres of a BRT Station"
      }
    ],
    "titles": [
      {
        "title": "LIS_PROD.LDR.Jomet_Building_Footprints_Shape"
      }
    ],
    "immutableResource": {
      "resourceURL": "download link unavailable"
    }
  },
  {
    "linkedResources": [
      {
        "linkedResourceType": "Metadata",
        "resourceDescription": "Original Metadata Record",
        "resourceURL": "http://oa.dirisa.org/Institutions/coj/coj/metadata/meta15242388316/getOriginalXml"
      }
    ],
    "publisher": "City of Johannesburg",
    "rightsList": [
      {
        "rights": "This resource does not have an open license - use is restricted due to restricted.",
        "rightsURI": "https://creativecommons.org/licenses/by/4.0/"
      }
    ],
    "publicationYear": "2018",
    "formats": [
      [
        "SDE Feature Class",
        "Arcinfo"
      ]
    ],
    "language": "en-US",
    "contributors": [
      {
        "nameIdentifiers": [
          {
            "nameIdentifierScheme": "",
            "schemeURI": "",
            "nameIdentifier": ""
          }
        ],
        "givenName": "",
        "name": "Projects Section",
        "contributorType": "Other",
        "affiliations": [
          {
            "affiliation": "Organisation: City of Johannesburg;  Position Name: Manager"
          }
        ],
        "familyName": ""
      },
      {
        "nameIdentifiers": [
          {
            "nameIdentifierScheme": "",
            "schemeURI": "",
            "nameIdentifier": ""
          }
        ],
        "givenName": "",
        "name": "Projects Section",
        "contributorType": "Other",
        "affiliations": [
          {
            "affiliation": "Organisation: City of Johannesburg;  Position Name: Manager"
          }
        ],
        "familyName": ""
      },
      {
        "nameIdentifiers": [
          {
            "nameIdentifierScheme": "",
            "schemeURI": "",
            "nameIdentifier": ""
          }
        ],
        "givenName": "",
        "name": "Projects Section",
        "contributorType": "Other",
        "affiliations": [
          {
            "affiliation": "Organisation: City of Johannesburg;  Position Name: Manager"
          }
        ],
        "familyName": ""
      },
      {
        "nameIdentifiers": [
          {
            "nameIdentifierScheme": "",
            "schemeURI": "",
            "nameIdentifier": ""
          }
        ],
        "givenName": "",
        "name": "Projects Section",
        "contributorType": "DataCurator",
        "affiliations": [
          {
            "affiliation": "Organisation: City of Johannesburg;  Position Name: Manager"
          }
        ],
        "familyName": ""
      }
    ],
    "geoLocations": [
      {
        "geoLocationBox": "POLYGON ((-26.537485 27.700707, -26.537485 28.224807, -25.891644 28.224807, -25.891644 27.700707, -26.537485 27.700707))"
      }
    ],
    "dates": [
      {
        "date": {
          "lte": "2018-04-13",
          "gte": "2018-04-13"
        },
        "dateType": "Created"
      },
      {
        "date": {
          "lte": "2018-04-13",
          "gte": "2018-04-13"
        },
        "dateType": "inForce"
      },
      {
        "date": {
          "lte": "2018-04-19",
          "gte": "2018-04-19"
        },
        "dateType": "Issued"
      }
    ],
    "identifier": {
      "identifier": "8b4cef1c3b70cce8ec78b7a9116a4e4a",
      "identifierType": "plone-id"
    },
    "version": "1.2",
    "resourceType": {
      "resourceType": "mapDigital",
      "resourceTypeGeneral": "Dataset"
    },
    "alternateIdentifiers": [
      {
        "alternateIdentifierType": "Plone",
        "alternateIdentifier": "8b4cef1c3b70cce8ec78b7a9116a4e4a"
      }
    ],
    "subjects": [
      {
        "subject": "Downloadable Data"
      },
      {
        "subject": "5m contours"
      }
    ],
    "subtitle": "",
    "creators": [
      {
        "nameType": "",
        "nameIdentifiers": [
          {
            "nameIdentifierScheme": "",
            "schemeURI": "",
            "nameIdentifier": ""
          }
        ],
        "givenName": "",
        "name": "Corporate Geo-Informatics",
        "affiliations": [
          {
            "affiliation": "Organisation: City of Johannesburg;  Position Name: Manager"
          }
        ],
        "familyName": ""
      }
    ],
    "descriptions": [
      {
        "descriptionType": "Abstract",
        "description": "Five meter(5m) interval contours with heights generated from 2015 aerial photography."
      }
    ],
    "titles": [
      {
        "title": "LIS_PROD.LDR.Contours_5m"
      }
    ],
    "immutableResource": {
      "resourceURL": "download link unavailable"
    }
  },
  {
    "linkedResources": [
      {
        "linkedResourceType": "Metadata",
        "resourceDescription": "Original Metadata Record",
        "resourceURL": "http://oa.dirisa.org/Institutions/coj/coj/metadata/meta156319544496/getOriginalXml"
      }
    ],
    "publisher": "Heritage, arts and culture",
    "rightsList": [
      {
        "rights": "",
        "rightsURI": "https://creativecommons.org/licenses/by/4.0/"
      }
    ],
    "publicationYear": "2010",
    "formats": [
      [
        "File Geodatabase Feature Class",
        "ArcGis "
      ]
    ],
    "language": "en-US",
    "contributors": [
      {
        "nameIdentifiers": [
          {
            "nameIdentifierScheme": "",
            "schemeURI": "",
            "nameIdentifier": ""
          }
        ],
        "givenName": "",
        "name": "Eric Itzkin",
        "contributorType": "DataCurator",
        "affiliations": [
          {
            "affiliation": "Organisation: Heritage, arts and culture;  Position Name: Deputy Director;  e-Mail Address: Erici@joburg.org.za;  Delivery Point: African Museum;  City: Newtown, Johannesburg;  Province: Gauteng;  Postal Code: 2000"
          }
        ],
        "familyName": ""
      },
      {
        "nameIdentifiers": [
          {
            "nameIdentifierScheme": "",
            "schemeURI": "",
            "nameIdentifier": ""
          }
        ],
        "givenName": "",
        "name": "Eric Itzkin",
        "contributorType": "DataCurator",
        "affiliations": [
          {
            "affiliation": "Organisation: Heritage, arts and culture;  Position Name: Deputy Director;  e-Mail Address: Erici@joburg.org.za;  Delivery Point: African Museum;  City: Newtown, Johannesburg;  Province: Gauteng;  Postal Code: 2000"
          }
        ],
        "familyName": ""
      },
      {
        "nameIdentifiers": [
          {
            "nameIdentifierScheme": "",
            "schemeURI": "",
            "nameIdentifier": ""
          }
        ],
        "givenName": "",
        "name": "Eric Itzkin",
        "contributorType": "Other",
        "affiliations": [
          {
            "affiliation": "Organisation: Heritage, arts and culture;  Position Name: Deputy Director;  e-Mail Address: Erici@joburg.org.za;  Delivery Point: African Museum;  City: Newtown, Johannesburg;  Province: Gauteng;  Postal Code: 2000"
          }
        ],
        "familyName": ""
      }
    ],
    "geoLocations": [
      {
        "geoLocationBox": "POLYGON ((-26.352688 27.81469, -26.352688 28.146835, -25.943191 28.146835, -25.943191 27.81469, -26.352688 27.81469))"
      }
    ],
    "dates": [
      {
        "date": {
          "lte": "2010-11-01",
          "gte": "2010-11-01"
        },
        "dateType": "Created"
      },
      {
        "date": {
          "lte": "2019-07-15",
          "gte": "2019-07-15"
        },
        "dateType": "Issued"
      }
    ],
    "identifier": {
      "identifier": "9749b0f16f09a7160345a0c11ca95c14",
      "identifierType": "plone-id"
    },
    "version": "1.2",
    "resourceType": {
      "resourceType": "mapDigital",
      "resourceTypeGeneral": "Dataset"
    },
    "alternateIdentifiers": [
      {
        "alternateIdentifierType": "Plone",
        "alternateIdentifier": "9749b0f16f09a7160345a0c11ca95c14"
      }
    ],
    "subjects": [
      {
        "subject": "Downloadable Data"
      }
    ],
    "subtitle": "",
    "creators": [
      {
        "nameType": "",
        "nameIdentifiers": [
          {
            "nameIdentifierScheme": "",
            "schemeURI": "",
            "nameIdentifier": ""
          }
        ],
        "givenName": "",
        "name": "Eric Itzkin",
        "affiliations": [
          {
            "affiliation": "Organisation: Heritage, arts and culture;  Position Name: Deputy Director;  e-Mail Address: Erici@joburg.org.za;  Delivery Point: African Museum;  City: Newtown, Johannesburg;  Province: Gauteng;  Postal Code: 2000"
          }
        ],
        "familyName": ""
      }
    ],
    "descriptions": [
      {
        "descriptionType": "Abstract",
        "description": "Heritage sites within the CoJ. Several datasets were integrated to arrive at the Heritage sites"
      }
    ],
    "titles": [
      {
        "title": "Heritage_Sites"
      }
    ],
    "immutableResource": {
      "resourceURL": "download link unavailable"
    }
  },
  {
    "linkedResources": [
      {
        "linkedResourceType": "Metadata",
        "resourceDescription": "Original Metadata Record",
        "resourceURL": "http://oa.dirisa.org/Institutions/coj/coj/metadata/meta155861271884/getOriginalXml"
      }
    ],
    "publisher": "City of Johannesburg Metropolitan",
    "rightsList": [
      {
        "rights": "",
        "rightsURI": "https://creativecommons.org/licenses/by/4.0/"
      }
    ],
    "publicationYear": "2019",
    "formats": [
      [
        "Shapefile",
        ""
      ]
    ],
    "language": "en-US",
    "geoLocations": [
      {
        "geoLocationBox": "POLYGON ((-26.481643 27.806342, -26.481643 28.192381, -25.922616 28.192381, -25.922616 27.806342, -26.481643 27.806342))"
      }
    ],
    "dates": [
      {
        "date": {
          "lte": "2019-05-23",
          "gte": "2019-05-23"
        },
        "dateType": "Issued"
      }
    ],
    "identifier": {
      "identifier": "3c59cb8c5b947c5c03fbab9347f483d4",
      "identifierType": "plone-id"
    },
    "version": "2007",
    "resourceType": {
      "resourceType": "mapDigital",
      "resourceTypeGeneral": "Dataset"
    },
    "alternateIdentifiers": [
      {
        "alternateIdentifierType": "Plone",
        "alternateIdentifier": "3c59cb8c5b947c5c03fbab9347f483d4"
      }
    ],
    "subjects": [
      {
        "subject": "Downloadable Data"
      },
      {
        "subject": "Point Data form"
      },
      {
        "subject": "City of Johannesburg"
      }
    ],
    "subtitle": "",
    "creators": [
      {
        "nameType": "",
        "nameIdentifiers": [
          {
            "nameIdentifierScheme": "",
            "schemeURI": "",
            "nameIdentifier": ""
          }
        ],
        "givenName": "",
        "name": "City of Johannesburg Metropolitan",
        "affiliations": [
          {
            "affiliation": "City of Johannesburg Metropolitan"
          }
        ],
        "familyName": ""
      }
    ],
    "descriptions": [
      {
        "descriptionType": "Abstract",
        "description": "A point Features depicting locality of the FireStations within the COJ.A shapefile form EMS with fields e.g.Cat_Type, Description, Address, Station Commander, Station number,Tel number, Fax number,Cell number and Region"
      }
    ],
    "titles": [
      {
        "title": "Fire_Stations_New"
      }
    ],
    "immutableResource": {
      "resourceURL": "download link unavailable"
    }
  },
  {
    "linkedResources": [
      {
        "linkedResourceType": "Metadata",
        "resourceDescription": "Original Metadata Record",
        "resourceURL": "http://oa.dirisa.org/Institutions/coj/coj/metadata/meta156112224184/getOriginalXml"
      }
    ],
    "publisher": "Environment Infrastructure and Services, City of Joburg.",
    "rightsList": [
      {
        "rights": "",
        "rightsURI": "https://creativecommons.org/licenses/by/4.0/"
      }
    ],
    "publicationYear": "2018",
    "formats": [
      [
        "SDE Feature Class",
        "10.2"
      ]
    ],
    "language": "en-US",
    "contributors": [
      {
        "nameIdentifiers": [
          {
            "nameIdentifierScheme": "",
            "schemeURI": "",
            "nameIdentifier": ""
          }
        ],
        "givenName": "",
        "name": "Emma Netshilulu",
        "contributorType": "DataCurator",
        "affiliations": [
          {
            "affiliation": "Organisation: Environment Infrastructure and Services, City of Joburg.;  Position Name: GIS"
          }
        ],
        "familyName": ""
      }
    ],
    "dates": [
      {
        "date": {
          "lte": "2019-06-21",
          "gte": "2019-06-21"
        },
        "dateType": "Issued"
      }
    ],
    "identifier": {
      "identifier": "b02ead3b9f18aa889c4801c38c201a25",
      "identifierType": "plone-id"
    },
    "version": "1.2",
    "resourceType": {
      "resourceType": "mapDigital",
      "resourceTypeGeneral": "Dataset"
    },
    "alternateIdentifiers": [
      {
        "alternateIdentifierType": "Plone",
        "alternateIdentifier": "b02ead3b9f18aa889c4801c38c201a25"
      }
    ],
    "subjects": [
      {
        "subject": "Downloadable Data"
      },
      {
        "subject": "Records of decision for the city of Johannesburg."
      }
    ],
    "subtitle": "",
    "creators": [
      {
        "nameType": "",
        "nameIdentifiers": [
          {
            "nameIdentifierScheme": "",
            "schemeURI": "",
            "nameIdentifier": ""
          }
        ],
        "givenName": "",
        "name": "Emma Netshilulu",
        "affiliations": [
          {
            "affiliation": "Organisation: Environment Infrastructure and Services, City of Joburg.;  Position Name: GIS"
          }
        ],
        "familyName": ""
      }
    ],
    "descriptions": [
      {
        "descriptionType": "Abstract",
        "description": "Records of decision for the city of Johannesburg.Geometry type: PolygonUpdate Frequency: AnnuallyLast Update: 06 June 2019"
      }
    ],
    "titles": [
      {
        "title": "LIS_PROD.LDR.EIA_RoD"
      }
    ],
    "immutableResource": {
      "resourceURL": "download link unavailable"
    }
  },
  {
    "linkedResources": [
      {
        "linkedResourceType": "Metadata",
        "resourceDescription": "Original Metadata Record",
        "resourceURL": "http://oa.dirisa.org/Institutions/coj/coj/metadata/metadata.2017-06-30.0955089190/getOriginalXml"
      }
    ],
    "publisher": "Corporate Geo-Informatics (CGIS)",
    "rightsList": [
      {
        "rights": "",
        "rightsURI": "https://creativecommons.org/licenses/by/4.0/"
      }
    ],
    "publicationYear": "2017",
    "formats": [
      [
        "SDE Feature Class",
        "ArcGIS 10.2.2"
      ]
    ],
    "language": "en-US",
    "contributors": [
      {
        "nameIdentifiers": [
          {
            "nameIdentifierScheme": "",
            "schemeURI": "",
            "nameIdentifier": ""
          }
        ],
        "givenName": "",
        "name": "Corporate Geo- Informatics (CGIS)",
        "contributorType": "ContactPerson",
        "affiliations": [
          {
            "affiliation": "Position Name: Projects Section; e-Mail Address: cgisprojects@joburg.org.za; City: Johannesburg; Province: Gauteng; Delivery Point: Metro Centre, 158 Civic Boulevard, Braamfontein; Postal Code: 2000"
          }
        ],
        "familyName": ""
      },
      {
        "nameIdentifiers": [
          {
            "nameIdentifierScheme": "",
            "schemeURI": "",
            "nameIdentifier": ""
          }
        ],
        "givenName": "",
        "name": "Projects Section",
        "contributorType": "ContactPerson",
        "affiliations": [
          {
            "affiliation": "Position Name: Manager; e-Mail Address: cgisprojects@joburg.org.za; City: Johannesburg; Province: Gauteng; Delivery Point: Metro Center, 158 Civic Boulevard, Braamfontein; Postal Code: 2000"
          }
        ],
        "familyName": ""
      },
      {
        "nameIdentifiers": [
          {
            "nameIdentifierScheme": "",
            "schemeURI": "",
            "nameIdentifier": ""
          }
        ],
        "givenName": "",
        "name": "Spatial Information Section, Data Administration and Mapping",
        "contributorType": "DataCurator",
        "affiliations": [
          {
            "affiliation": "Position Name: Manager"
          }
        ],
        "familyName": ""
      }
    ],
    "geoLocations": [
      {
        "geoLocationBox": "POLYGON ((-26.52383 27.715483, -26.52383 28.214965, -25.914662 28.214965, -25.914662 27.715483, -26.52383 27.715483))"
      }
    ],
    "identifier": {
      "identifier": "ff195f516f0058c0bd3f24f5ccc8f2b6",
      "identifierType": "plone-id"
    },
    "version": "1.2",
    "resourceType": {
      "resourceType": "mapDigital",
      "resourceTypeGeneral": "Dataset"
    },
    "alternateIdentifiers": [
      {
        "alternateIdentifierType": "Plone",
        "alternateIdentifier": "ff195f516f0058c0bd3f24f5ccc8f2b6"
      }
    ],
    "subjects": [
      {
        "subject": "Johannesburg"
      },
      {
        "subject": "Johannesburg Township boundaries"
      },
      {
        "subject": "Downloadable Data"
      }
    ],
    "subtitle": "",
    "creators": [
      {
        "nameType": "",
        "nameIdentifiers": [
          {
            "nameIdentifierScheme": "",
            "schemeURI": "",
            "nameIdentifier": ""
          }
        ],
        "givenName": "",
        "name": "City of Johannesburg Metropolitan",
        "affiliations": [
          {
            "affiliation": "City of Johannesburg Metropolitan"
          }
        ],
        "familyName": ""
      }
    ],
    "descriptions": [
      {
        "descriptionType": "Abstract",
        "description": "Polygon feature class denoting township features. Description of Pseudo codes used by Corporate GIS Due to Maraisburg Ext.1 which has a TSG_ID of T0IQ0241001, we have adopted a TSG_ID code of T0IQ0241999 for Maraisburg Extension. Similarly the following apply:- Diepkloof ext => T0IQ0543991 Florida ext => T0IQ0121991 Greenside ext => T0IR0286991 Highlands North ext => T0IR0308991 Linden ext => T0IQ0220991 Maraisburg ext => T0IQ0241991 Observatory ext => T0IR0488991 Orlando west ext => T0IQ0567991 Parktown ext => T0IR0502991 Pimville Zone 1 => T0IQ0576901 Pimville Zone 1 Ext => T0IQ0576800 Pimville Zone 2 => T0IQ0576902 Pimville Zone 3 => T0IQ0576903 Pimville Zone 4 => T0IQ0576904 Pimville Zone 5 => T0IQ0576905 Pimville Zone 6 => T0IQ0576906 Pimville Zone 7 => T0IQ0576907 Pimville Zone 8 => T0IQ0576908 Pimville Zone 9 => T0IQ0576909 Rosettenville ext => T0IR0575991 West cliff ext => T0IR0724991 West Turffontein ext => T0IR0723991 N.B. REMAINDERS ARE NOT BEING UPDATED."
      }
    ],
    "titles": [
      {
        "title": "LIS_PROD.LIS.SP_TOWNSHIP"
      }
    ],
    "immutableResource": {
      "resourceURL": "download link unavailable"
    }
  },
  {
    "publicationYear": "2011",
    "userId": "",
    "contributors": [
      {
        "nameIdentifiers": [
          {
            "nameIdentifierScheme": "",
            "schemeURI": "",
            "nameIdentifier": ""
          }
        ],
        "givenName": "",
        "name": "Michael Silberbauer",
        "contributorType": "ContactPerson",
        "affiliations": [
          {
            "affiliation": "Department of Water and Sanitation, Private Bag X313, Pretoria, 0001, South Africa"
          }
        ],
        "familyName": ""
      },
      {
        "nameIdentifiers": [
          {
            "nameIdentifierScheme": "",
            "schemeURI": "",
            "nameIdentifier": ""
          }
        ],
        "givenName": "",
        "name": "South African Environmental Observation Network",
        "contributorType": "Distributor",
        "affiliations": [
          {
            "affiliation": "SAEON - National Office, PO Box 2600, Pretoria, 0001, South Africa"
          }
        ],
        "familyName": ""
      }
    ],
    "identifier": {
      "identifier": "10.15493/SARVA.DWS.10000021",
      "identifierType": "DOI"
    },
    "userVersion": "",
    "owner": "",
    "subtitle": "",
    "titles": [
      {
        "titleType": "",
        "title": "River profile classification Catchment U"
      }
    ],
    "linkedResources": [
      {
        "linkedResourceType": "Query",
        "resourceDescription": "River profile classification Catchment U",
        "resourceURL": "http://app01.saeon.ac.za:8080/geoserver/DWA_shp/wms?service=WMS&version=1.1.0&request=GetMap&layers=DWA_shp:mainstemsu-ll&styles=&bbox=29.293541,-30.614706,31.411373,-28.943768&width=512&height=403&srs=EPSG:4326&format=application/openlayers"
      }
    ],
    "dates": [
      {
        "date": {
          "lte": "2005",
          "gte": "2005"
        },
        "dateType": "Collected"
      }
    ],
    "publisher": "Department of Water and Sanitation",
    "language": "en-US",
    "geoLocations": [
      {
        "geoLocationBox": "POLYGON ((-35.126 14.88, -35.126 33.34, -22.126 33.34, -22.126 14.88, -35.126 14.88))"
      }
    ],
    "relatedIdentifiers": [
      {
        "schemeType": "http://datacite.org/schema/kernel-3",
        "relatedIdentifier": "http://datacite.org/schema/kernel-3",
        "relatedIdentifierType": "URL",
        "relationType": "HasMetadata"
      }
    ],
    "resourceType": {
      "resourceType": "on",
      "resourceTypeGeneral": "Dataset"
    },
    "immutableResource": {
      "resourceURL": "http://media.dirisa.org/inventory/archive/spatial/dws/mainstemsu-ll.zip",
      "resourceDescription": "River profile classification Catchment U"
    },
    "subjects": [
      {
        "schemeURI": "",
        "subjectScheme": "",
        "subject": "Biodiversity"
      },
      {
        "schemeURI": "",
        "subjectScheme": "",
        "subject": " Bird Area"
      },
      {
        "schemeURI": "",
        "subjectScheme": "",
        "subject": " River Catchment"
      },
      {
        "schemeURI": "",
        "subjectScheme": "",
        "subject": " WMS"
      },
      {
        "schemeURI": "",
        "subjectScheme": "",
        "subject": " GEOSS data core"
      },
      {
        "schemeURI": "",
        "subjectScheme": "",
        "subject": " Water"
      }
    ],
    "rightsList": [
      {
        "rights": "Attribution-ShareAlike 4.0 International (CC BY-SA 4.0)",
        "rightsURI": "https://creativecommons.org/licenses/by-sa/4.0/legalcode"
      }
    ],
    "creators": [
      {
        "nameType": "",
        "nameIdentifiers": [
          {
            "nameIdentifierScheme": "",
            "schemeURI": "",
            "nameIdentifier": ""
          }
        ],
        "givenName": "",
        "name": "Department of Water and Sanitation",
        "affiliations": [
          {
            "affiliation": "Private Bag X313, Pretoria, 0001, South Africa"
          }
        ],
        "familyName": ""
      }
    ],
    "descriptions": [
      {
        "descriptionType": "Abstract",
        "description": "Longitudinal slope profiles derived for all 1:500 000 rivers of South Africa, including cross-border catchments extending into neighbouring countries. River main stems are identified by a unique reach number (REACHNUM) within each primary catchment."
      }
    ],
    "alternateIdentifiers": [
      {
        "alternateIdentifierType": "Plone",
        "alternateIdentifier": "21493f5859edc92f331ed61e7eab2966"
      }
    ]
  },
  {
    "publicationYear": "2011",
    "userId": "",
    "contributors": [
      {
        "nameIdentifiers": [
          {
            "nameIdentifierScheme": "",
            "schemeURI": "",
            "nameIdentifier": ""
          }
        ],
        "givenName": "",
        "name": "Michael Silberbauer",
        "contributorType": "ContactPerson",
        "affiliations": [
          {
            "affiliation": "Department of Water and Sanitation, Private Bag X313, Pretoria, 0001, South Africa"
          }
        ],
        "familyName": ""
      },
      {
        "nameIdentifiers": [
          {
            "nameIdentifierScheme": "",
            "schemeURI": "",
            "nameIdentifier": ""
          }
        ],
        "givenName": "",
        "name": "South African Environmental Observation Network",
        "contributorType": "Distributor",
        "affiliations": [
          {
            "affiliation": "SAEON - National Office, PO Box 2600, Pretoria, 0001, South Africa"
          }
        ],
        "familyName": ""
      }
    ],
    "identifier": {
      "identifier": "10.15493/SARVA.DWS.10000015",
      "identifierType": "DOI"
    },
    "userVersion": "",
    "owner": "",
    "subtitle": "",
    "titles": [
      {
        "titleType": "",
        "title": "River profile classification Catchment N"
      }
    ],
    "linkedResources": [
      {
        "linkedResourceType": "Query",
        "resourceDescription": "River profile classification Catchment N",
        "resourceURL": "http://app01.saeon.ac.za:8080/geoserver/DWA_shp/wms?service=WMS&version=1.1.0&request=GetMap&layers=DWA_shp:mainstemsn-ll&styles=&bbox=23.797525,-33.722095,26.150091,-31.715935&width=512&height=436&srs=EPSG:4326&format=application/openlayers"
      }
    ],
    "dates": [
      {
        "date": {
          "lte": "2005",
          "gte": "2005"
        },
        "dateType": "Collected"
      }
    ],
    "publisher": "Department of Water and Sanitation",
    "language": "en-US",
    "geoLocations": [
      {
        "geoLocationBox": "POLYGON ((-35.126 14.88, -35.126 33.34, -22.126 33.34, -22.126 14.88, -35.126 14.88))"
      }
    ],
    "relatedIdentifiers": [
      {
        "schemeType": "http://datacite.org/schema/kernel-3",
        "relatedIdentifier": "http://datacite.org/schema/kernel-3",
        "relatedIdentifierType": "URL",
        "relationType": "HasMetadata"
      }
    ],
    "resourceType": {
      "resourceType": "on",
      "resourceTypeGeneral": "Dataset"
    },
    "immutableResource": {
      "resourceURL": "http://media.dirisa.org/inventory/archive/spatial/dws/mainstemsn-ll.zip",
      "resourceDescription": "River profile classification Catchment N"
    },
    "subjects": [
      {
        "schemeURI": "",
        "subjectScheme": "",
        "subject": "Biodiversity"
      },
      {
        "schemeURI": "",
        "subjectScheme": "",
        "subject": " Bird Area"
      },
      {
        "schemeURI": "",
        "subjectScheme": "",
        "subject": " River Catchment"
      },
      {
        "schemeURI": "",
        "subjectScheme": "",
        "subject": " WMS"
      },
      {
        "schemeURI": "",
        "subjectScheme": "",
        "subject": " GEOSS data core"
      },
      {
        "schemeURI": "",
        "subjectScheme": "",
        "subject": " Water"
      }
    ],
    "rightsList": [
      {
        "rights": "Attribution-ShareAlike 4.0 International (CC BY-SA 4.0)",
        "rightsURI": "https://creativecommons.org/licenses/by-sa/4.0/legalcode"
      }
    ],
    "creators": [
      {
        "nameType": "",
        "nameIdentifiers": [
          {
            "nameIdentifierScheme": "",
            "schemeURI": "",
            "nameIdentifier": ""
          }
        ],
        "givenName": "",
        "name": "Department of Water and Sanitation",
        "affiliations": [
          {
            "affiliation": "Private Bag X313, Pretoria, 0001, South Africa"
          }
        ],
        "familyName": ""
      }
    ],
    "descriptions": [
      {
        "descriptionType": "Abstract",
        "description": "Longitudinal slope profiles derived for all 1:500 000 rivers of South Africa, including cross-border catchments extending into neighbouring countries. River main stems are identified by a unique reach number (REACHNUM) within each primary catchment."
      }
    ],
    "alternateIdentifiers": [
      {
        "alternateIdentifierType": "Plone",
        "alternateIdentifier": "1d6d6e6334d7a5142e3287d7494243f4"
      }
    ]
  },
  {
    "publicationYear": "2011",
    "userId": "",
    "contributors": [
      {
        "nameIdentifiers": [
          {
            "nameIdentifierScheme": "",
            "schemeURI": "",
            "nameIdentifier": ""
          }
        ],
        "givenName": "",
        "name": "Michael Silberbauer",
        "contributorType": "ContactPerson",
        "affiliations": [
          {
            "affiliation": "Department of Water and Sanitation, Private Bag X313, Pretoria, 0001, South Africa"
          }
        ],
        "familyName": ""
      },
      {
        "nameIdentifiers": [
          {
            "nameIdentifierScheme": "",
            "schemeURI": "",
            "nameIdentifier": ""
          }
        ],
        "givenName": "",
        "name": "South African Environmental Observation Network",
        "contributorType": "Distributor",
        "affiliations": [
          {
            "affiliation": "SAEON - National Office, PO Box 2600, Pretoria, 0001, South Africa"
          }
        ],
        "familyName": ""
      }
    ],
    "identifier": {
      "identifier": "10.15493/SARVA.DWS.10000008",
      "identifierType": "DOI"
    },
    "userVersion": "",
    "owner": "",
    "subtitle": "",
    "titles": [
      {
        "titleType": "",
        "title": "River profile classification Catchment D"
      }
    ],
    "linkedResources": [
      {
        "linkedResourceType": "Query",
        "resourceDescription": "River profile classification Catchment D",
        "resourceURL": "http://app01.saeon.ac.za:8080/geoserver/DWA_shp/wms?service=WMS&version=1.1.0&request=GetMap&layers=DWA_shp:mainstemsd-ll&styles=&bbox=15.98333,-32.661224,29.450325,-21.814405&width=512&height=412&srs=EPSG:4326&format=application/openlayers"
      }
    ],
    "dates": [
      {
        "date": {
          "lte": "2005",
          "gte": "2005"
        },
        "dateType": "Collected"
      }
    ],
    "publisher": "Department of Water and Sanitation",
    "language": "en-US",
    "geoLocations": [
      {
        "geoLocationBox": "POLYGON ((-35.126 14.88, -35.126 33.34, -22.126 33.34, -22.126 14.88, -35.126 14.88))"
      }
    ],
    "relatedIdentifiers": [
      {
        "schemeType": "http://datacite.org/schema/kernel-3",
        "relatedIdentifier": "http://datacite.org/schema/kernel-3",
        "relatedIdentifierType": "URL",
        "relationType": "HasMetadata"
      }
    ],
    "resourceType": {
      "resourceType": "on",
      "resourceTypeGeneral": "Dataset"
    },
    "immutableResource": {
      "resourceURL": "http://media.dirisa.org/inventory/archive/spatial/dws/mainstemsd-ll.zip",
      "resourceDescription": "River profile classification Catchment D"
    },
    "subjects": [
      {
        "schemeURI": "",
        "subjectScheme": "",
        "subject": "Biodiversity"
      },
      {
        "schemeURI": "",
        "subjectScheme": "",
        "subject": " Bird Area"
      },
      {
        "schemeURI": "",
        "subjectScheme": "",
        "subject": " River Catchment"
      },
      {
        "schemeURI": "",
        "subjectScheme": "",
        "subject": " WMS"
      },
      {
        "schemeURI": "",
        "subjectScheme": "",
        "subject": " GEOSS data core"
      },
      {
        "schemeURI": "",
        "subjectScheme": "",
        "subject": " Water"
      }
    ],
    "rightsList": [
      {
        "rights": "Attribution-ShareAlike 4.0 International (CC BY-SA 4.0)",
        "rightsURI": "https://creativecommons.org/licenses/by-sa/4.0/legalcode"
      }
    ],
    "creators": [
      {
        "nameType": "",
        "nameIdentifiers": [
          {
            "nameIdentifierScheme": "",
            "schemeURI": "",
            "nameIdentifier": ""
          }
        ],
        "givenName": "",
        "name": "Department of Water and Sanitation",
        "affiliations": [
          {
            "affiliation": "Private Bag X313, Pretoria, 0001, South Africa"
          }
        ],
        "familyName": ""
      }
    ],
    "descriptions": [
      {
        "descriptionType": "Abstract",
        "description": "Longitudinal slope profiles derived for all 1:500 000 rivers of South Africa, including cross-border catchments extending into neighbouring countries. River main stems are identified by a unique reach number (REACHNUM) within each primary catchment."
      }
    ],
    "alternateIdentifiers": [
      {
        "alternateIdentifierType": "Plone",
        "alternateIdentifier": "709d9fc41b994db63935c510c4457b6d"
      }
    ]
  }
]